dashai_mlp_model_fran/__init__.py
dashai_mlp_model_fran/dataloader_class_template.py
dashai_mlp_model_fran/metric_class_template.py
dashai_mlp_model_fran/model_class_template.py
dashai_mlp_model_fran/task_class_template.py
dashai_mlp_model_fran-0.0.7.dist-info/METADATA
dashai_mlp_model_fran-0.0.7.dist-info/WHEEL
dashai_mlp_model_fran-0.0.7.dist-info/entry_points.txt
dashai_mlp_model_fran-0.0.7.dist-info/RECORD
