Metadata-Version: 2.3
Name: dashai_mlp_model_fran
Version: 0.0.7
Summary: DashAI Plugin description
Author: fran
Author-email: francisca.cona@ug.uchile.cl
Keywords: Model
Requires-Python: >=3.8
